dqdatasdk/__init__.py
dqdatasdk/_internal.py
dqdatasdk/_version.py
dqdatasdk/client.py
dqdatasdk/connection.py
dqdatasdk/connection_pool.py
dqdatasdk/decorators.py
dqdatasdk/thread_local.py
dqdatasdk/utils.py
dqdatasdk/validators.py
dqdatasdk/dqmodules/__init__.py
dqdatasdk/dqmodules/dqcertificate.py
dqdatasdk/services/__init__.py
dqdatasdk/services/basic.py
dqdatasdk/services/calendar.py
dqdatasdk/services/concept.py
dqdatasdk/services/consensus.py
dqdatasdk/services/constant.py
dqdatasdk/services/convertible.py
dqdatasdk/services/factor.py
dqdatasdk/services/financial.py
dqdatasdk/services/future.py
dqdatasdk/services/get_capital_flow.py
dqdatasdk/services/get_price.py
dqdatasdk/services/index.py
dqdatasdk/services/ksh_auction_info.py
dqdatasdk/services/live.py
dqdatasdk/services/live_md_client.py
dqdatasdk/services/market_data.py
dqdatasdk/services/options.py
dqdatasdk/services/shenwan.py
dqdatasdk/services/stock_status.py
dqdatasdk/services/structured_fund.py
dqdatasdk/services/tmall.py
dqdatasdk/services/xueqiu.py
dqdatasdk/services/detail/__init__.py
dqdatasdk/services/detail/adjust_price.py
dqdatasdk/services/detail/get_price_df.py
dqdatasdk/services/detail/resample_helper.py
dqdatasdk/services/orm/__init__.py
dqdatasdk/services/orm/balance_sheet_sql.py
dqdatasdk/services/orm/cash_flow_sql.py
dqdatasdk/services/orm/eod_derivative_indicator_sql.py
dqdatasdk/services/orm/financial_indicator_sql.py
dqdatasdk/services/orm/fundamental_base_sql.py
dqdatasdk/services/orm/income_statement_sql.py
dqdatasdk/services/orm/pit_financials.py
dqdatasdk/services/orm/pit_financials_ex.py
dqdatasdk/services/orm/ttm_sql.py
dqdatasdk/share/__init__.py
dqdatasdk/share/codec.py
dqdatasdk/share/errors.py
dqdatasdk/share/protocol.py
dqmodules/__init__.py
dqmodules/_version.py
dqmodules/dqdatasdk.py
dqmodules/dqmodule/__init__.py
dqmodules/dqmodule/dqcertificate.py
dqmodules/dqmodule/overwriteif.py
dqmodules/dqmodule/print_redirect.py
dqdatasdk-2.9.45.2.dist-info/METADATA
dqdatasdk-2.9.45.2.dist-info/WHEEL
dqdatasdk-2.9.45.2.dist-info/top_level.txt
dqdatasdk-2.9.45.2.dist-info/RECORD
