Metadata-Version: 2.1
Name: dqdatasdk
Version: 2.9.45.2
Summary: dqdatasdk api system
Home-page: 
Author: digquant
Author-email: it@digquant.com
License: LICENSE
Keywords: dqdatasdk
Platform: UNKNOWN
Requires-Dist: rqdatac (<=2.9.46,>=2.9.46)
Requires-Dist: requests
